kivy_latex_label/__init__.py
kivy_latex_label/latex_label.kv
kivy_latex_label/latex_label.py
kivy_latex_label-1.0.9.dist-info/METADATA
kivy_latex_label-1.0.9.dist-info/WHEEL
kivy_latex_label-1.0.9.dist-info/licenses/LICENSE
kivy_latex_label-1.0.9.dist-info/RECORD
