Metadata-Version: 2.4
Name: kivy-latex-label
Version: 1.0.9
Summary: A package that defines a new label class for Kivy to display text with LaTeX equations.
Project-URL: Homepage, https://github.com/PaulCreusy/kivy-latex-label
Project-URL: Issues, https://github.com/PaulCreusy/kivy-latex-label/issues
Project-URL: Documentation, https://github.com/PaulCreusy/kivy-latex-label
Author-email: PaulCreusy <paul.creusy@gmail.com>
License-File: LICENSE
Keywords: kivy,label,latex
Classifier: License :: OSI Approved :: MIT License
Classifier: Operating System :: OS Independent
Classifier: Programming Language :: Python :: 3
Requires-Python: >=3.10
Requires-Dist: kivy>=2.0.0
Requires-Dist: matplotlib>=3.8.0
Requires-Dist: pillow
